PyStasm-0.3.1.data/headers/asm.h
PyStasm-0.3.1.data/headers/atface.h
PyStasm-0.3.1.data/headers/basedesc.h
PyStasm-0.3.1.data/headers/classicdesc.h
PyStasm-0.3.1.data/headers/convshape.h
PyStasm-0.3.1.data/headers/err.h
PyStasm-0.3.1.data/headers/eyedet.h
PyStasm-0.3.1.data/headers/eyedist.h
PyStasm-0.3.1.data/headers/facedet.h
PyStasm-0.3.1.data/headers/faceroi.h
PyStasm-0.3.1.data/headers/hat.h
PyStasm-0.3.1.data/headers/hatdesc.h
PyStasm-0.3.1.data/headers/initasm.h
PyStasm-0.3.1.data/headers/landmarks.h
PyStasm-0.3.1.data/headers/landtab_muct77.h
PyStasm-0.3.1.data/headers/misc.h
PyStasm-0.3.1.data/headers/pinstart.h
PyStasm-0.3.1.data/headers/print.h
PyStasm-0.3.1.data/headers/shape17.h
PyStasm-0.3.1.data/headers/shapehacks.h
PyStasm-0.3.1.data/headers/shapemod.h
PyStasm-0.3.1.data/headers/startshape.h
PyStasm-0.3.1.data/headers/stasm.h
PyStasm-0.3.1.data/headers/stasm_landmarks.h
PyStasm-0.3.1.data/headers/stasm_lib.h
PyStasm-0.3.1.data/headers/stasm_lib_ext.h
PyStasm-0.3.1.data/headers/yaw00.mh
PyStasm-0.3.1.data/headers/yaw00_lev0_p00_classic.mh
PyStasm-0.3.1.data/headers/yaw00_lev0_p01_classic.mh
PyStasm-0.3.1.data/headers/yaw00_lev0_p02_classic.mh
PyStasm-0.3.1.data/headers/yaw00_lev0_p03_classic.mh
PyStasm-0.3.1.data/headers/yaw00_lev0_p04_classic.mh
PyStasm-0.3.1.data/headers/yaw00_lev0_p05_classic.mh
PyStasm-0.3.1.data/headers/yaw00_lev0_p06_classic.mh
PyStasm-0.3.1.data/headers/yaw00_lev0_p07_classic.mh
PyStasm-0.3.1.data/headers/yaw00_lev0_p08_classic.mh
PyStasm-0.3.1.data/headers/yaw00_lev0_p09_classic.mh
PyStasm-0.3.1.data/headers/yaw00_lev0_p10_classic.mh
PyStasm-0.3.1.data/headers/yaw00_lev0_p11_classic.mh
PyStasm-0.3.1.data/headers/yaw00_lev0_p12_classic.mh
PyStasm-0.3.1.data/headers/yaw00_lev0_p13_classic.mh
PyStasm-0.3.1.data/headers/yaw00_lev0_p14_classic.mh
PyStasm-0.3.1.data/headers/yaw00_lev0_p15_classic.mh
PyStasm-0.3.1.data/headers/yaw00_lev0_p16_hat.mh
PyStasm-0.3.1.dist-info/DESCRIPTION.rst
PyStasm-0.3.1.dist-info/METADATA
PyStasm-0.3.1.dist-info/RECORD
PyStasm-0.3.1.dist-info/WHEEL
PyStasm-0.3.1.dist-info/metadata.json
PyStasm-0.3.1.dist-info/top_level.txt
