Metadata-Version: 2.0
Name: PyStasm
Version: 0.3.1
Summary: Python wrapper for finding features in faces.
Home-page: http://github.com/mjszczep/PyStasm
Author: Matthew Szczepankiewicz
Author-email: mjszczep@buffalo.edu
License: Simplified BSD
Platform: Linux
Platform: Windows
Classifier: Programming Language :: C++
Classifier: Programming Language :: Python :: 2
Classifier: Programming Language :: Python :: 3
Classifier: Operating System :: Microsoft :: Windows
Classifier: Operating System :: Unix
Classifier: Topic :: Software Development :: Libraries
Classifier: Topic :: Scientific/Engineering :: Image Recognition
Classifier: Intended Audience :: Developers
Classifier: Intended Audience :: Science/Research
Classifier: Development Status :: 3 - Alpha
Classifier: License :: OSI Approved :: BSD License
Requires-Dist: numpy (>=1.7)
